{
  "animals": [
    {
      "id": 2,
      "name": "Decker",
      "breed": "German Shepherd"
    },
    {
      "id": 3,
      "name": "Esme",
      "breed": "Pitbull"
    },
    {
      "id": 5,
      "name": "Pickles",
      "breed": "Beagle"
    },
    {
      "id": 6,
      "name": "Ollivander",
      "breed": "Great Dane"
    },
    {
      "name": "Bjorn",
      "breed": "Husky",
      "id": 7
    },
    {
      "name": "Beanie ",
      "breed": "Dachshund",
      "id": 8
    }
  ],
  "employees": [
    {
      "id": 1,
      "name": "Brenda Long",
      "position": "Dog Lover!"
    },
    {
      "id": 2,
      "name": "Roey Wiz",
      "position": "Dog Lover!"
    },
    {
      "id": 3,
      "name": "Sage Klein",
      "position": "Dog Lover!"
    },
    {
      "id": 4,
      "name": "Chad Jones",
      "position": "Dog Lover!"
    },
    {
      "id": 5,
      "name": "Rob Mixon",
      "position": "Dog Lover!"
    },
    {
      "id": 6,
      "name": "Brett Derrington",
      "position": "Dog Lover!"
    },
    {
      "name": "Trevor Aldridge ",
      "position": "Groomer",
      "id": 7
    }
  ],
  "locations": [
    {
      "id": 1,
      "name": "Nashville North"
    },
    {
      "id": 4,
      "name": "Nashville West"
    },
    {
      "name": "Brentwood",
      "id": 5
    }
  ],
  "owners": [
    {
      "id": 1,
      "phoneNumber": "(615)555-5555",
      "name": "Bobby Baybay"
    },
    {
      "id": 2,
      "phoneNumber": "(615)123-4567",
      "name": "Dolly Parton"
    },
    {
      "name": "Chen Kenichi",
      "phoneNumber": "(417)382-2342",
      "id": 3
    }
  ]
}